README.rst
setup.py
nscaweb/__init__.py
nscaweb/authentication.py
nscaweb/communication.py
nscaweb/main.py
nscaweb/server.py
nscaweb.egg-info/PKG-INFO
nscaweb.egg-info/SOURCES.txt
nscaweb.egg-info/dependency_links.txt
nscaweb.egg-info/entry_points.txt
nscaweb.egg-info/namespace_packages.txt
nscaweb.egg-info/not-zip-safe
nscaweb.egg-info/requires.txt
nscaweb.egg-info/top_level.txt