Metadata-Version: 1.1
Name: nscaweb
Version: 0.1.20
Summary: A more feature rich alternative than the classic NSCA daemon.
Home-page: https://github.com/smetj/nscaweb
Author: Jelle Smet
Author-email: development@smetj.net
License: UNKNOWN
Download-URL: https://github.com/smetj/nscaweb/tarball/master
Platform: Linux
Classifier: Development Status :: 4 - Beta
Classifier: License :: OSI Approved :: GNU General Public License v3 or later (GPLv3+)
Classifier: Programming Language :: Python
Classifier: Programming Language :: Python :: 2
Classifier: Programming Language :: Python :: 2.6
Classifier: Programming Language :: Python :: 2.7
Classifier: Intended Audience :: System Administrators
